libelium_parking_sensor_v2/__init__.py
libelium_parking_sensor_v2/decoder.py
libelium_parking_sensor_v2-0.1.2.dist-info/licenses/LICENSE
libelium_parking_sensor_v2-0.1.2.dist-info/METADATA
libelium_parking_sensor_v2-0.1.2.dist-info/WHEEL
libelium_parking_sensor_v2-0.1.2.dist-info/top_level.txt
libelium_parking_sensor_v2-0.1.2.dist-info/RECORD
