Metadata-Version: 2.4
Name: libelium-parking-sensor-v2
Version: 0.1.2
Summary: Add your description here
Requires-Python: >=3.10
License-File: LICENSE
Requires-Dist: incremental>=24.11.0
Requires-Dist: pydantic>=2.12.5
Requires-Dist: setuptools>=61.0.0
Dynamic: license-file
